main.py
transcode.py
dvtag/__init__.py
dvtag/_doujin_voice.py
dvtag/_dvtag.py
dvtag/_scrape.py
dvtag/_utils.py
dvtag-0.7.7.dist-info/licenses/LICENSE
dvtag-0.7.7.dist-info/METADATA
dvtag-0.7.7.dist-info/WHEEL
dvtag-0.7.7.dist-info/entry_points.txt
dvtag-0.7.7.dist-info/top_level.txt
dvtag-0.7.7.dist-info/RECORD
