Metadata-Version: 2.4
Name: dvtag
Version: 0.7.7
Summary: A command-line tool designed to tag your doujin voice library.
Home-page: https://github.com/nobekanai/dvtag
Author: Nobe Kanai
Author-email: nobekanai@gmail.com
Classifier: Programming Language :: Python :: 3
Classifier: License :: OSI Approved :: MIT License
Classifier: Operating System :: OS Independent
Requires-Python: >=3.9
License-File: LICENSE
Requires-Dist: certifi
Requires-Dist: charset-normalizer
Requires-Dist: idna
Requires-Dist: mutagen
Requires-Dist: natsort
Requires-Dist: Pillow
Requires-Dist: requests
Requires-Dist: urllib3
Dynamic: license-file
